umwelt/__init__.py
umwelt/decoders/__init__.py
umwelt/decoders/jsonlike.py
umwelt/errors.py
umwelt/interface.py
umwelt-2019.8.2.dist-info/WHEEL
umwelt-2019.8.2.dist-info/METADATA
umwelt-2019.8.2.dist-info/RECORD
