Metadata-Version: 2.1
Name: umwelt
Version: 2019.8.2
Summary: Configure your program via environment variables, validated by pydantic.
Home-page: https://github.com/thilp/umwelt
License: MIT
Author: Thibaut Le Page
Author-email: thilp@thilp.net
Requires-Python: >=3.6,<4.0
Classifier: License :: OSI Approved :: MIT License
Classifier: Programming Language :: Python :: 3
Classifier: Programming Language :: Python :: 3.6
Classifier: Programming Language :: Python :: 3.7
Requires-Dist: pydantic (>=0.17,<1)
Project-URL: Repository, https://github.com/thilp/umwelt
